README.md
setup.cfg
setup.py
sour_cereal/__about__.py
sour_cereal/__init__.py
sour_cereal/auth_source_connection.py
sour_cereal/session_source_connection.py
sour_cereal/source_connection.py
sour_cereal.egg-info/PKG-INFO
sour_cereal.egg-info/SOURCES.txt
sour_cereal.egg-info/dependency_links.txt
sour_cereal.egg-info/top_level.txt
sour_cereal/base/__init__.py
sour_cereal/base/extraction.py
sour_cereal/base/source_connection_interface.py