Metadata-Version: 2.1
Name: sour-cereal
Version: 1.0.2
Summary: An abstraction of data source for extraction applications usage
Home-page: https://github.com/CarlosAdp/sour-cereal
Author: Carlos Alberto Duarte Pinto
Author-email: carlos.adpinto@gmail.com
License: MIT
Download-URL: https://github.com/CarlosAdp/sour-cereal
Keywords: abstraction,data extraction,data sources,interface,etl
Platform: UNKNOWN
Classifier: Programming Language :: Python :: 3.6
Classifier: Programming Language :: Python :: 3.7
Classifier: Programming Language :: Python :: 3.8
Classifier: Operating System :: OS Independent
Classifier: Topic :: Utilities
Classifier: License :: OSI Approved :: MIT License
Classifier: Intended Audience :: Developers
